deform_extensions/__init__.py
deform_extensions/test_it.py
deform_extensions/__pycache__/__init__.cpython-37-pytest-6.2.1.pyc
deform_extensions/__pycache__/__init__.cpython-37.pyc
deform_extensions/__pycache__/__init__.cpython-38.pyc
deform_extensions/__pycache__/__init__.cpython-39-pytest-6.2.5.pyc
deform_extensions/__pycache__/__init__.cpython-39.pyc
deform_extensions/__pycache__/test_it.cpython-37-pytest-6.2.1.pyc
deform_extensions/__pycache__/test_it.cpython-39-pytest-6.2.5.pyc
deform_extensions/resources/checkbox_toggle.js
deform_extensions/resources/date.js
deform_extensions/resources/radio_choice_toggle.js
deform_extensions/templates/accordion_form.pt
deform_extensions/templates/accordion_mapping.pt
deform_extensions/templates/accordions_mapping.pt
deform_extensions/templates/checkbox_toggle.pt
deform_extensions/templates/chosen_optgroup.pt
deform_extensions/templates/datetimeinput.pt
deform_extensions/templates/disabledinput.pt
deform_extensions/templates/grid_form.pt
deform_extensions/templates/grid_mapping.pt
deform_extensions/templates/grid_mapping_item.pt
deform_extensions/templates/inline_mapping.pt
deform_extensions/templates/inline_mapping_item.pt
deform_extensions/templates/radio_choice_toggle.pt
deform_extensions-0.9.dist-info/LICENSE.txt
deform_extensions-0.9.dist-info/METADATA
deform_extensions-0.9.dist-info/WHEEL
deform_extensions-0.9.dist-info/entry_points.txt
deform_extensions-0.9.dist-info/top_level.txt
deform_extensions-0.9.dist-info/RECORD
