Metadata-Version: 2.1
Name: deform_extensions
Version: 0.9
Summary: Usefull tools for making grid/accordion layouted forms
Home-page: https://github.com/majerteam/deform_extensions
Author: Gaston Tjebbes - Majerti
Author-email: tech@majerti.fr
License: GPLv3
Classifier: Environment :: Web Environment
Classifier: Intended Audience :: Developers
Classifier: License :: OSI Approved :: GNU General Public License v3 (GPLv3)
Classifier: Operating System :: OS Independent
Classifier: Programming Language :: Python
Classifier: Programming Language :: Python :: 2.7
Classifier: Topic :: Internet :: WWW/HTTP
Classifier: Topic :: Internet :: WWW/HTTP :: Dynamic Content
License-File: LICENSE.txt
Requires-Dist: deform
Requires-Dist: js.deform
Requires-Dist: js.jquery-timepicker-addon
Requires-Dist: js.jqueryui
Requires-Dist: js.underscore
